setup.py
colorinche/__init__.py
colorinche/extensions.py
colorinche.egg-info/PKG-INFO
colorinche.egg-info/SOURCES.txt
colorinche.egg-info/dependency_links.txt
colorinche.egg-info/requires.txt
colorinche.egg-info/top_level.txt