Metadata-Version: 1.0
Name: colorinche
Version: 0.0.3
Summary: Lets you use Jinja2 to generate output for the console.
Home-page: http://pypi.python.org/pypi/colorinche/
Author: Felipe Lerena
Author-email: felipelerena@gmail.com
License: LICENSE.txt
Platform: UNKNOWN
